ai_tools_ct/__init__.py
ai_tools_ct/data_generator.py
ai_tools_ct/gpt.py
ai_tools_ct-0.0.4.dist-info/METADATA
ai_tools_ct-0.0.4.dist-info/WHEEL
ai_tools_ct-0.0.4.dist-info/licenses/LICENSE
ai_tools_ct-0.0.4.dist-info/RECORD
